autotest/__init__.py
autotest/lib/__init__.py
autotest/lib/setup.py
autotest/lib/base/__init__.py
autotest/lib/base/commons.py
autotest/lib/base/setup.py
autotest/lib/base/webActions.py
autotest/lib/client_builder/__init__.py
autotest/lib/client_builder/aws/__init__.py
autotest/lib/client_builder/aws/client.py
autotest/lib/client_builder/aws/dynamodb.py
autotest/lib/client_builder/aws/lambda_obj.py
autotest/lib/configurations/__init__.py
autotest/lib/configurations/common_config.py
autotest/lib/generator/__init__.py
autotest/lib/generator/generate_test_data.py
autotest/lib/generator/graph.py
autotest/lib/generator/initialize.py
autotest/lib/generator/question_type.py
autotest/lib/generator/test_data.py
autotest/lib/generator/utils.py
autotest/lib/generator/intent/__init__.py
autotest/lib/generator/intent/intent.py
autotest/lib/lib/__init__.py
autotest/lib/lib/lend_event.py
autotest/lib/lib/node/__init__.py
autotest/lib/lib/node/action.py
autotest/lib/lib/node/node.py
autotest/lib/runner/__init__.py
autotest/lib/runner/initializer.py
autotest/lib/runner/application_overview/__init__.py
autotest/lib/runner/application_overview/runner.py
autotest/lib/runner/application_workflow/__init__.py
autotest/lib/runner/application_workflow/runner.py
autotest/lib/utilities/__init__.py
autotest/lib/utilities/random_email.py
lendsmart_autotest-2.4.dist-info/METADATA
lendsmart_autotest-2.4.dist-info/WHEEL
lendsmart_autotest-2.4.dist-info/top_level.txt
lendsmart_autotest-2.4.dist-info/RECORD
