Metadata-Version: 2.1
Name: lendsmart-autotest
Version: 2.4
Summary: The internal SDK for lendsmart autotest
Home-page: https://bitbucket.org/lendsmartlabs/lendsmart_py/
Author: Lendsmart
Author-email: infos@lendsmart.ai
License: MIT
Keywords: lendsmart autotest
Classifier: Programming Language :: Python :: 3.8
Classifier: Programming Language :: Python :: 3.9
Classifier: Programming Language :: Python :: 3.10
Requires-Dist: Faker
Requires-Dist: PyAutoGUI
Requires-Dist: boto3
Requires-Dist: importlib-metadata
Requires-Dist: keyboard
Requires-Dist: networkx
Requires-Dist: pytest
Requires-Dist: pytest-html
Requires-Dist: ramda
Requires-Dist: requests
Requires-Dist: selenium (==3.8.0)
Requires-Dist: urllib3
Requires-Dist: webdriver-manager
